{
  "interactive-discover-1": {
    "v0": {
      "n_results": 0,
      "n_http_requests": 1,
      "execution_time": {
        "average": 92.94411191999912,
        "min": 89.61187300000165,
        "max": 97.36828199999582,
        "std": 2.328709389657441
      }
    },
    "v1": {
      "n_results": 0,
      "n_http_requests": 1,
      "execution_time": {
        "average": 92.53904228000057,
        "min": 88.21086600000854,
        "max": 101.67586499999743,
        "std": 2.8174625639557616
      }
    },
    "v2": {
      "n_results": 0,
      "n_http_requests": 1,
      "execution_time": {
        "average": 85.15449792,
        "min": 81.88969999999972,
        "max": 92.87432800000533,
        "std": 2.5360962135155503
      }
    },
    "v3": {
      "n_results": 0,
      "n_http_requests": 1,
      "execution_time": {
        "average": 102.99719649999984,
        "min": 98.31833599999663,
        "max": 114.1442939999979,
        "std": 3.0903460495975237
      }
    },
    "v4": {
      "n_results": 0,
      "n_http_requests": 1,
      "execution_time": {
        "average": 92.77127470000094,
        "min": 89.34123800000816,
        "max": 105.50095099999453,
        "std": 3.432390615025036
      }
    }
  },
  "interactive-discover-2": {
    "v0": {
      "n_results": 0,
      "n_http_requests": 1,
      "execution_time": {
        "average": 100.07124315999914,
        "min": 95.05116499999713,
        "max": 106.74555700000201,
        "std": 2.724971621091786
      }
    },
    "v1": {
      "n_results": 0,
      "n_http_requests": 1,
      "execution_time": {
        "average": 99.90671274000022,
        "min": 96.09720400000515,
        "max": 114.47656399999687,
        "std": 4.039831330112562
      }
    },
    "v2": {
      "n_results": 0,
      "n_http_requests": 1,
      "execution_time": {
        "average": 91.62956707999955,
        "min": 87.38325299999269,
        "max": 96.538836000007,
        "std": 2.4337726545578477
      }
    },
    "v3": {
      "n_results": 0,
      "n_http_requests": 1,
      "execution_time": {
        "average": 111.12025338000065,
        "min": 106.37734599999385,
        "max": 118.16830900000059,
        "std": 3.107771109446453
      }
    },
    "v4": {
      "n_results": 0,
      "n_http_requests": 1,
      "execution_time": {
        "average": 98.39497519999917,
        "min": 95.10279000000446,
        "max": 103.52120499999728,
        "std": 2.2462930450865093
      }
    }
  },
  "interactive-discover-3": {
    "v0": {
      "n_results": 0,
      "n_http_requests": 1,
      "execution_time": {
        "average": 100.38375308000018,
        "min": 95.11673500000325,
        "max": 108.94053599999461,
        "std": 2.9192626939966955
      }
    },
    "v1": {
      "n_results": 0,
      "n_http_requests": 1,
      "execution_time": {
        "average": 99.77495383999776,
        "min": 95.71448500000406,
        "max": 112.39637599998969,
        "std": 2.8099224234443057
      }
    },
    "v2": {
      "n_results": 0,
      "n_http_requests": 1,
      "execution_time": {
        "average": 92.73781424000045,
        "min": 88.46634299999278,
        "max": 98.4045860000042,
        "std": 2.6167357122172135
      }
    },
    "v3": {
      "n_results": 0,
      "n_http_requests": 1,
      "execution_time": {
        "average": 110.02078820000024,
        "min": 106.38191099998949,
        "max": 119.54662800001097,
        "std": 2.6823373257147702
      }
    },
    "v4": {
      "n_results": 0,
      "n_http_requests": 1,
      "execution_time": {
        "average": 99.36848358000162,
        "min": 96.14755900000455,
        "max": 104.26517800000147,
        "std": 2.2747645743550304
      }
    }
  },
  "interactive-discover-4": {
    "v0": {
      "n_results": 0,
      "n_http_requests": 2,
      "execution_time": {
        "average": 113.66774106000085,
        "min": 107.87215700000525,
        "max": 130.1652960000065,
        "std": 4.324489993225225
      }
    },
    "v1": {
      "n_results": 0,
      "n_http_requests": 2,
      "execution_time": {
        "average": 112.21392412000074,
        "min": 107.68589100000099,
        "max": 121.69548599999689,
        "std": 2.765629395207144
      }
    },
    "v2": {
      "n_results": 0,
      "n_http_requests": 2,
      "execution_time": {
        "average": 104.5191475399991,
        "min": 99.73578399998951,
        "max": 122.88920999999391,
        "std": 3.6089535458294826
      }
    },
    "v3": {
      "n_results": 0,
      "n_http_requests": 2,
      "execution_time": {
        "average": 123.32138794000173,
        "min": 117.86033899999165,
        "max": 131.3147170000011,
        "std": 3.207771200914481
      }
    },
    "v4": {
      "n_results": 0,
      "n_http_requests": 2,
      "execution_time": {
        "average": 112.44924417999981,
        "min": 107.73598100000527,
        "max": 129.69602499999746,
        "std": 4.0201438676676675
      }
    }
  },
  "interactive-discover-5": {
    "v0": {
      "n_results": 0,
      "n_http_requests": 1,
      "execution_time": {
        "average": 79.20154689999995,
        "min": 74.70060599999852,
        "max": 87.30138699999952,
        "std": 2.5530317157727556
      }
    },
    "v1": {
      "n_results": 0,
      "n_http_requests": 1,
      "execution_time": {
        "average": 79.041016639999,
        "min": 73.87624199999846,
        "max": 92.2013719999959,
        "std": 3.649766963199054
      }
    },
    "v2": {
      "n_results": 0,
      "n_http_requests": 1,
      "execution_time": {
        "average": 71.67807413999981,
        "min": 66.30554499999562,
        "max": 75.65243100000953,
        "std": 2.2871556413018257
      }
    },
    "v3": {
      "n_results": 0,
      "n_http_requests": 1,
      "execution_time": {
        "average": 89.16786706000043,
        "min": 85.46092099999078,
        "max": 94.41895300000033,
        "std": 2.524824679368178
      }
    },
    "v4": {
      "n_results": 0,
      "n_http_requests": 1,
      "execution_time": {
        "average": 78.15642397999967,
        "min": 73.66398699999263,
        "max": 86.45144900000014,
        "std": 2.4896884491197673
      }
    }
  },
  "interactive-discover-6": {
    "v0": {
      "n_results": 0,
      "n_http_requests": 1,
      "execution_time": {
        "average": 89.4006727400003,
        "min": 83.45042799999646,
        "max": 100.58363300000201,
        "std": 2.8152036561857035
      }
    },
    "v1": {
      "n_results": 0,
      "n_http_requests": 1,
      "execution_time": {
        "average": 89.30032652000052,
        "min": 85.66027100000065,
        "max": 100.74417099999846,
        "std": 3.125818100378466
      }
    },
    "v2": {
      "n_results": 0,
      "n_http_requests": 1,
      "execution_time": {
        "average": 82.1051343000005,
        "min": 76.68676300000516,
        "max": 98.74753700000292,
        "std": 3.3594048361070348
      }
    },
    "v3": {
      "n_results": 0,
      "n_http_requests": 1,
      "execution_time": {
        "average": 100.0174412800002,
        "min": 95.4853679999942,
        "max": 121.06899300000805,
        "std": 4.354518641040055
      }
    },
    "v4": {
      "n_results": 0,
      "n_http_requests": 1,
      "execution_time": {
        "average": 88.9607260600009,
        "min": 85.24404600000707,
        "max": 98.85846299999685,
        "std": 2.840719058040615
      }
    }
  },
  "interactive-discover-7": {
    "v0": {
      "n_results": 0,
      "n_http_requests": 1,
      "execution_time": {
        "average": 93.18496519999987,
        "min": 89.38410999999905,
        "max": 104.95290000000386,
        "std": 3.421527293834455
      }
    },
    "v1": {
      "n_results": 0,
      "n_http_requests": 1,
      "execution_time": {
        "average": 92.18435207999951,
        "min": 88.51332599998568,
        "max": 99.336553000001,
        "std": 2.7477791168645855
      }
    },
    "v2": {
      "n_results": 0,
      "n_http_requests": 1,
      "execution_time": {
        "average": 85.42165108000103,
        "min": 81.5751820000005,
        "max": 93.5383509999956,
        "std": 2.4426948317605204
      }
    },
    "v3": {
      "n_results": 0,
      "n_http_requests": 1,
      "execution_time": {
        "average": 102.17600615999865,
        "min": 96.40165299999353,
        "max": 105.2752760000003,
        "std": 2.4355995642655084
      }
    },
    "v4": {
      "n_results": 0,
      "n_http_requests": 1,
      "execution_time": {
        "average": 91.86001201999956,
        "min": 86.74671399999352,
        "max": 95.53191700000025,
        "std": 2.2493549320214496
      }
    }
  },
  "interactive-discover-8": {
    "v0": {
      "timeout": 120000
    },
    "v1": {
      "timeout": 120000
    },
    "v2": {
      "timeout": 120000
    },
    "v3": {
      "timeout": 120000
    },
    "v4": {
      "timeout": 120000
    }
  },
  "interactive-short-1": {
    "v0": {
      "n_results": 1,
      "n_http_requests": 2,
      "execution_time": {
        "average": 160.65818736000045,
        "min": 155.14564000000246,
        "max": 176.13616399999592,
        "std": 4.382322816073422
      }
    },
    "v1": {
      "n_results": 1,
      "n_http_requests": 2,
      "execution_time": {
        "average": 160.8055343800009,
        "min": 154.04378199999337,
        "max": 192.06314399999974,
        "std": 6.317705034199675
      }
    },
    "v2": {
      "n_results": 1,
      "n_http_requests": 2,
      "execution_time": {
        "average": 152.60589152,
        "min": 147.13371900000493,
        "max": 158.07915800000774,
        "std": 3.178898548825182
      }
    },
    "v3": {
      "n_results": 1,
      "n_http_requests": 2,
      "execution_time": {
        "average": 171.8284669400024,
        "min": 164.76552299999457,
        "max": 186.12561799999094,
        "std": 5.011215897921148
      }
    },
    "v4": {
      "n_results": 1,
      "n_http_requests": 2,
      "execution_time": {
        "average": 158.81976803999947,
        "min": 153.07956099999137,
        "max": 169.71648899999855,
        "std": 3.6494546550130544
      }
    }
  },
  "interactive-short-2": {
    "v0": {
      "n_results": 0,
      "n_http_requests": 1,
      "execution_time": {
        "average": 164.58212750000064,
        "min": 159.72579399999813,
        "max": 181.03715000000375,
        "std": 3.9990373311614853
      }
    },
    "v1": {
      "n_results": 0,
      "n_http_requests": 1,
      "execution_time": {
        "average": 163.81879832000007,
        "min": 159.65756000000692,
        "max": 170.52687900001183,
        "std": 3.0073009792531322
      }
    },
    "v2": {
      "n_results": 0,
      "n_http_requests": 1,
      "execution_time": {
        "average": 154.77708753999818,
        "min": 148.82546800001,
        "max": 172.5110289999866,
        "std": 3.9306377076459906
      }
    },
    "v3": {
      "n_results": 0,
      "n_http_requests": 1,
      "execution_time": {
        "average": 177.15565850000073,
        "min": 171.43646899999294,
        "max": 186.14001799999096,
        "std": 3.5715280803992573
      }
    },
    "v4": {
      "n_results": 0,
      "n_http_requests": 1,
      "execution_time": {
        "average": 163.01995163999965,
        "min": 157.37311699999555,
        "max": 169.52270999999018,
        "std": 3.142897178033599
      }
    }
  },
  "interactive-short-3": {
    "v0": {
      "timeout": 120000
    },
    "v1": {
      "timeout": 120000
    },
    "v2": {
      "timeout": 120000
    },
    "v3": {
      "timeout": 120000
    },
    "v4": {
      "timeout": 120000
    }
  },
  "interactive-short-4": {
    "v0": {
      "n_results": 1,
      "n_http_requests": 1,
      "execution_time": {
        "average": 519.2046292600021,
        "min": 471.7910989999946,
        "max": 596.4710710000072,
        "std": 28.886695965023293
      }
    },
    "v1": {
      "n_results": 1,
      "n_http_requests": 1,
      "execution_time": {
        "average": 587.0271134200005,
        "min": 538.1361920000054,
        "max": 633.3334650000033,
        "std": 29.49726236586331
      }
    },
    "v2": {
      "n_results": 1,
      "n_http_requests": 2,
      "execution_time": {
        "average": 91.32052705999959,
        "min": 88.27843599999323,
        "max": 96.61387699999614,
        "std": 2.3569459701820454
      }
    },
    "v3": {
      "n_results": 1,
      "n_http_requests": 2,
      "execution_time": {
        "average": 108.18441711999971,
        "min": 102.07690800000273,
        "max": 116.2348720000009,
        "std": 3.104013973263794
      }
    },
    "v4": {
      "n_results": 1,
      "n_http_requests": 1,
      "execution_time": {
        "average": 436.5550115,
        "min": 403.4207979999919,
        "max": 485.003131999998,
        "std": 21.0567820898406
      }
    }
  },
  "interactive-short-5": {
    "v0": {
      "n_results": 1,
      "n_http_requests": 14,
      "execution_time": {
        "average": 600.4289135600012,
        "min": 565.8768980000023,
        "max": 636.7701410000009,
        "std": 20.873985887468898
      }
    },
    "v1": {
      "n_results": 1,
      "n_http_requests": 24,
      "execution_time": {
        "average": 936.2149783600008,
        "min": 864.9071100000001,
        "max": 1038.254786000005,
        "std": 43.908004295076516
      }
    },
    "v2": {
      "n_results": 1,
      "n_http_requests": 89,
      "execution_time": {
        "average": 2991.13755522,
        "min": 2714.402018000008,
        "max": 3337.881913999998,
        "std": 177.94138677732514
      }
    },
    "v3": {
      "n_results": 1,
      "n_http_requests": 23,
      "execution_time": {
        "average": 458.8150473200006,
        "min": 400.61413800000446,
        "max": 546.7141859999974,
        "std": 30.307953190582438
      }
    },
    "v4": {
      "n_results": 1,
      "n_http_requests": 36,
      "execution_time": {
        "average": 1135.2833470399987,
        "min": 1040.5346040000004,
        "max": 1241.3045569999958,
        "std": 46.176932456642085
      }
    }
  },
  "interactive-short-6": {
    "v0": {
      "timeout": 120000
    },
    "v1": {
      "timeout": 120000
    },
    "v2": {
      "timeout": 120000
    },
    "v3": {
      "timeout": 120000
    },
    "v4": {
      "timeout": 120000
    }
  },
  "interactive-short-7": {
    "v0": {
      "timeout": 120000
    },
    "v1": {
      "timeout": 120000
    },
    "v2": {
      "timeout": 120000
    },
    "v3": {
      "timeout": 120000
    },
    "v4": {
      "timeout": 120000
    }
  }
}